odoo/addons/l10n_cl_electronic_invoicing/README.rst
odoo/addons/l10n_cl_electronic_invoicing/__init__.py
odoo/addons/l10n_cl_electronic_invoicing/__manifest__.py
odoo/addons/l10n_cl_electronic_invoicing/controllers/__init__.py
odoo/addons/l10n_cl_electronic_invoicing/controllers/boleta.py
odoo/addons/l10n_cl_electronic_invoicing/controllers/downloader.py
odoo/addons/l10n_cl_electronic_invoicing/data/ir_cron.xml
odoo/addons/l10n_cl_electronic_invoicing/data/ir_sequence.xml
odoo/addons/l10n_cl_electronic_invoicing/data/partner.activities.csv
odoo/addons/l10n_cl_electronic_invoicing/data/product_template.xml
odoo/addons/l10n_cl_electronic_invoicing/data/res.currency.csv
odoo/addons/l10n_cl_electronic_invoicing/data/res_country.xml
odoo/addons/l10n_cl_electronic_invoicing/data/res_partner.xml
odoo/addons/l10n_cl_electronic_invoicing/data/sii.concept.type.csv
odoo/addons/l10n_cl_electronic_invoicing/data/sii.document.class.csv
odoo/addons/l10n_cl_electronic_invoicing/data/sii.document.letter.csv
odoo/addons/l10n_cl_electronic_invoicing/data/sii.regional.offices.csv
odoo/addons/l10n_cl_electronic_invoicing/data/sii_document_type.xml
odoo/addons/l10n_cl_electronic_invoicing/data/sii_responsability.xml
odoo/addons/l10n_cl_electronic_invoicing/demo/res_partner.xml
odoo/addons/l10n_cl_electronic_invoicing/i18n/es_CL.po
odoo/addons/l10n_cl_electronic_invoicing/i18n/l10n_cl_electronic_invoicing.pot
odoo/addons/l10n_cl_electronic_invoicing/models/__init__.py
odoo/addons/l10n_cl_electronic_invoicing/models/account_invoice.py
odoo/addons/l10n_cl_electronic_invoicing/models/account_invoice_line.py
odoo/addons/l10n_cl_electronic_invoicing/models/account_invoice_referencias.py
odoo/addons/l10n_cl_electronic_invoicing/models/account_journal.py
odoo/addons/l10n_cl_electronic_invoicing/models/account_journal_sii_document_class.py
odoo/addons/l10n_cl_electronic_invoicing/models/account_move.py
odoo/addons/l10n_cl_electronic_invoicing/models/account_move_line.py
odoo12_addon_l10n_cl_electronic_invoicing-12.0.1.0.0.99.dev2.dist-info/METADATA
odoo12_addon_l10n_cl_electronic_invoicing-12.0.1.0.0.99.dev2.dist-info/WHEEL
odoo12_addon_l10n_cl_electronic_invoicing-12.0.1.0.0.99.dev2.dist-info/top_level.txt
odoo12_addon_l10n_cl_electronic_invoicing-12.0.1.0.0.99.dev2.dist-info/RECORD
