Metadata-Version: 2.1
Name: odoo12-addon-l10n-cl-electronic-invoicing
Version: 12.0.1.0.0.99.dev2
Summary: Get your customer invoices signed by SII.
Home-page: https://github.com/OCA/l10n-chile
Author: Daniel Santibáñez Polanco, Cooperativa OdooCoop, Konos, Odoo Community Association (OCA)
Author-email: support@odoo-community.org
License: AGPL-3
Platform: UNKNOWN
Classifier: Programming Language :: Python
Classifier: Framework :: Odoo
Classifier: License :: OSI Approved :: GNU Affero General Public License v3
Classifier: Development Status :: 4 - Beta
Requires-Python: >=3.5
Requires-Dist: M2Crypto
Requires-Dist: cchardet
Requires-Dist: dicttoxml
Requires-Dist: num2words
Requires-Dist: odoo12-addon-l10n-cl-chart-of-account
Requires-Dist: odoo12-addon-l10n-cl-toponym
Requires-Dist: odoo12-addon-report-xlsx
Requires-Dist: odoo (<12.1dev,>=12.0a)
Requires-Dist: pdf417gen
Requires-Dist: pysftp
Requires-Dist: signxml
Requires-Dist: suds-jurko
Requires-Dist: urllib3
Requires-Dist: xlsxwriter
Requires-Dist: xmltodict
